LICENSE
README.md
pyproject.toml
setup.py
src/mcp_basicops/__init__.py
src/mcp_basicops/client.py
src/mcp_basicops/config.py
src/mcp_basicops/exceptions.py
src/mcp_basicops/py.typed
src/mcp_basicops/server.py
src/mcp_basicops/models/__init__.py
src/mcp_basicops/models/common.py
src/mcp_basicops/models/note.py
src/mcp_basicops/models/project.py
src/mcp_basicops/models/section.py
src/mcp_basicops/models/task.py
src/mcp_basicops/models/user.py
src/mcp_basicops/models/webhook.py
src/mcp_basicops/services/__init__.py
src/mcp_basicops/services/project.py
src/mcp_basicops/tools/__init__.py
src/mcp_basicops_server.egg-info/PKG-INFO
src/mcp_basicops_server.egg-info/SOURCES.txt
src/mcp_basicops_server.egg-info/dependency_links.txt
src/mcp_basicops_server.egg-info/entry_points.txt
src/mcp_basicops_server.egg-info/not-zip-safe
src/mcp_basicops_server.egg-info/requires.txt
src/mcp_basicops_server.egg-info/top_level.txt
tests/test_basic.py