Metadata-Version: 2.1
Name: mcp-basicops-server
Version: 0.1.0
Summary: MCP server for BasicOps project management platform integration
Home-page: https://github.com/yourusername/mcp-basicops-server
Author: MCP BasicOps Server
Author-email: MCP BasicOps Server <support@example.com>
License: MIT
Project-URL: Homepage, https://github.com/yourusername/mcp-basicops-server
Project-URL: Repository, https://github.com/yourusername/mcp-basicops-server.git
Project-URL: Issues, https://github.com/yourusername/mcp-basicops-server/issues
Project-URL: Documentation, https://github.com/yourusername/mcp-basicops-server#readme
Project-URL: Changelog, https://github.com/yourusername/mcp-basicops-server/releases
Keywords: mcp,basicops,project-management,llm,ai
Classifier: Development Status :: 4 - Beta
Classifier: Intended Audience :: Developers
Classifier: License :: OSI Approved :: MIT License
Classifier: Programming Language :: Python :: 3
Classifier: Programming Language :: Python :: 3.8
Classifier: Programming Language :: Python :: 3.9
Classifier: Programming Language :: Python :: 3.10
Classifier: Programming Language :: Python :: 3.11
Classifier: Programming Language :: Python :: 3.12
Classifier: Topic :: Software Development :: Libraries :: Python Modules
Classifier: Topic :: Office/Business :: Groupware
Classifier: Topic :: Internet :: WWW/HTTP :: Dynamic Content
Classifier: Operating System :: OS Independent
Requires-Python: >=3.8
Provides-Extra: dev
License-File: LICENSE
